{"data": 
	[{
		"row1": [{"col1": 10}, {"col2": 23}, {"col3": 19}, {"col4": 56}, {"col5": 78}, {"col6": 99}, {"col7": 54}]
	},
	{
		"row2": [{"col1": 10}, {"col2": 23}, {"col3": 19}, {"col4": 56}, {"col5": 78}, {"col6": 99}, {"col7": 54}]
	},
	{
		"row3": [{"col1": 10}, {"col2": 23}, {"col3": 19}, {"col4": 56}, {"col5": 78}, {"col6": 99}, {"col7": 54}]
	},
	{
		"row4": [{"col1": 10}, {"col2": 23}, {"col3": 19}, {"col4": 56}, {"col5": 78}, {"col6": 99}, {"col7": 54}]
	},
	{
		"row5": [{"col1": 10}, {"col2": 23}, {"col3": 19}, {"col4": 56}, {"col5": 78}, {"col6": 99}, {"col7": 54}]
	},
	{
		"row6": [{"col1": 10}, {"col2": 23}, {"col3": 19}, {"col4": 56}, {"col5": 78}, {"col6": 99}, {"col7": 54}]
	},
	{
		"row7": [{"col1": 10}, {"col2": 23}, {"col3": 19}, {"col4": 56}, {"col5": 78}, {"col6": 99}, {"col7": 54}]
	}
]}	